litestar_offline_docs/__init__.py
litestar_offline_docs/core.py
litestar_offline_docs/py.typed
litestar_offline_docs/testing.py
litestar_offline_docs/static/asyncapi-web-component.js
litestar_offline_docs/static/default.min.css
litestar_offline_docs/static/swagger-ui-bundle.js
litestar_offline_docs/static/swagger-ui-standalone-preset.js
litestar_offline_docs/static/swagger-ui.css
litestar_offline_docs-1.1.0.dist-info/METADATA
litestar_offline_docs-1.1.0.dist-info/WHEEL
litestar_offline_docs-1.1.0.dist-info/RECORD
