Metadata-Version: 2.4
Name: litestar-offline-docs
Version: 1.1.0
Summary: Offline API docs for Litestar
Author: community-of-python
Requires-Python: <4,>=3.9
Requires-Dist: litestar>=2.9.1
